cosmatch/__init__.py
cosmatch/classification/__init__.py
cosmatch/classification/classification.py
cosmatch/fake/__init__.py
cosmatch/fake/catalog_generator.py
cosmatch/load/__init__.py
cosmatch/load/disk_loader.py
cosmatch/load/neighbours_loader.py
cosmatch/load/utils.py
cosmatch/match/__init__.py
cosmatch/match/connection.py
cosmatch/match/data_handler.py
cosmatch/match/metrics.py
cosmatch/match/models/__init__.py
cosmatch/match/models/base.py
cosmatch/match/models/custom/__init__.py
cosmatch/match/models/custom/custom.py
cosmatch/match/models/custom/optimization.py
cosmatch/match/models/custom/predict_models.py
cosmatch/match/models/custom/prob_transformer.py
cosmatch/match/models/ml_models.py
cosmatch/match/models/nway_models.py
cosmatch/match/nway.py
cosmatch/match/pipeline.py
cosmatch/match/pretrained/hyperparams.pickle
cosmatch/match/union.py
cosmatch/preprocessing/__init__.py
cosmatch/preprocessing/duplicates.py
cosmatch/preprocessing/gaps.py
cosmatch/search/__init__.py
cosmatch/search/autoencoder.py
cosmatch/search/find_hmxb.py
cosmatch/search/io.py
cosmatch/search/read_catalogues.py
cosmatch/search/utils.py
cosmatch/settings.py
cosmatch/transforms.py
cosmatch/utils/__init__.py
cosmatch/utils/astrometry.py
cosmatch/utils/columns_handler.py
cosmatch/utils/io.py
cosmatch-0.1.4.dist-info/LICENSE
cosmatch-0.1.4.dist-info/METADATA
cosmatch-0.1.4.dist-info/WHEEL
cosmatch-0.1.4.dist-info/RECORD
