Metadata-Version: 2.1
Name: cosmatch
Version: 0.1.4
Summary: 
Author: Sbdjaro
Author-email: kir.tearo@yandex.ru
Requires-Python: >=3.10,<3.13
Classifier: Programming Language :: Python :: 3
Classifier: Programming Language :: Python :: 3.10
Classifier: Programming Language :: Python :: 3.11
Classifier: Programming Language :: Python :: 3.12
Provides-Extra: all
Provides-Extra: dev
Provides-Extra: docs
Provides-Extra: nway
Provides-Extra: style
Provides-Extra: tests
Requires-Dist: astropy (>=5.3.4,<6.0.0)
Requires-Dist: astroquery (>=0.4.6,<0.5.0)
Requires-Dist: catboost (>=1.2.2,<2.0.0)
Requires-Dist: flake8 (>=6.1.0,<7.0.0) ; extra == "style" or extra == "dev"
Requires-Dist: hyperopt (>=0.2.7,<0.3.0)
Requires-Dist: mypy (>=1.6.1,<2.0.0) ; extra == "style" or extra == "dev"
Requires-Dist: numpy (>=1.26.1,<2.0.0)
Requires-Dist: nway ; extra == "nway" or extra == "all"
Requires-Dist: pandas (>=2.1.1,<3.0.0)
Requires-Dist: pydocstyle (>=6.3.0,<7.0.0) ; extra == "style" or extra == "dev"
Requires-Dist: pygments (>=2.17.2,<3.0.0)
Requires-Dist: pytest (>=7.4.2,<8.0.0) ; extra == "tests" or extra == "dev"
Requires-Dist: pytest-cov (>=4.1.0,<5.0.0) ; extra == "tests" or extra == "dev"
Requires-Dist: requests (>=2.31.0,<3.0.0)
Requires-Dist: scikit-learn (>=1.3.1,<2.0.0)
Requires-Dist: setuptools (>=68.2.2,<69.0.0)
Requires-Dist: sphinx (>=7.2.6,<8.0.0) ; extra == "docs" or extra == "dev"
Requires-Dist: sphinx-autodoc-typehints (>=1.24.0,<2.0.0) ; extra == "docs" or extra == "dev"
Requires-Dist: sphinx-mathjax-offline (>=0.0.2,<0.0.3) ; extra == "docs" or extra == "dev"
